pt_library/__init__.py
pt_library/notifications.py
pt_library/pt_decorators.py
pt_library/pt_time.py
pt_library/sql.py
pt_library-0.1.7.dist-info/LICENSE
pt_library-0.1.7.dist-info/METADATA
pt_library-0.1.7.dist-info/WHEEL
pt_library-0.1.7.dist-info/top_level.txt
pt_library-0.1.7.dist-info/RECORD
