Metadata-Version: 2.1
Name: pt-library
Version: 0.1.7
Summary: A small utility package
Author-email: Smit Jethwa <smitjethwa20@gmail.com>
Project-URL: Documentation, https://pt-library.web.app/
Classifier: Programming Language :: Python :: 3
Classifier: License :: OSI Approved :: MIT License
Classifier: Operating System :: OS Independent
Requires-Python: >=3
License-File: LICENSE
Requires-Dist: urllib3 ==1.26.6
Requires-Dist: requests ==2.31.0
Requires-Dist: mysql-connector-python ==8.0.33
Requires-Dist: python-dateutil ==2.8.2
